source_asana/__init__.py
source_asana/components.py
source_asana/config_migration.py
source_asana/manifest.yaml
source_asana/run.py
source_asana/source.py
airbyte_source_asana-1.5.1.dist-info/METADATA
airbyte_source_asana-1.5.1.dist-info/WHEEL
airbyte_source_asana-1.5.1.dist-info/entry_points.txt
airbyte_source_asana-1.5.1.dist-info/RECORD
