Metadata-Version: 2.1
Name: airbyte-source-asana
Version: 1.5.1
Summary: Source implementation for asana.
Home-page: https://airbyte.com
License: ELv2
Author: Airbyte
Author-email: contact@airbyte.io
Requires-Python: >=3.10,<3.12
Classifier: License :: Other/Proprietary License
Classifier: Programming Language :: Python :: 3
Classifier: Programming Language :: Python :: 3.10
Classifier: Programming Language :: Python :: 3.11
Requires-Dist: airbyte-cdk (>=6,<7)
Project-URL: Documentation, https://docs.airbyte.com/integrations/sources/asana
Project-URL: Repository, https://github.com/airbytehq/airbyte
